README.md
setup.py
graphene_cerberus/__init__.py
graphene_cerberus.egg-info/PKG-INFO
graphene_cerberus.egg-info/SOURCES.txt
graphene_cerberus.egg-info/dependency_links.txt
graphene_cerberus.egg-info/requires.txt
graphene_cerberus.egg-info/top_level.txt